move_off_dockerhub/__init__.py
move_off_dockerhub-1.0.dist-info/LICENSE
move_off_dockerhub-1.0.dist-info/METADATA
move_off_dockerhub-1.0.dist-info/WHEEL
move_off_dockerhub-1.0.dist-info/entry_points.txt
move_off_dockerhub-1.0.dist-info/top_level.txt
move_off_dockerhub-1.0.dist-info/RECORD
