Metadata-Version: 2.1
Name: move-off-dockerhub
Version: 1.0
Summary: A simple commandline utility to copy many tags (regex filtered) of a docker image from one registry to another
Author-email: YuviPanda <yuvipanda@gmail.com>
Keywords: docker
Classifier: Programming Language :: Python :: 3
Classifier: License :: OSI Approved :: GNU Affero General Public License v3
Classifier: Operating System :: OS Independent
License-File: LICENSE
